README.rst
setup.py
afsk/__init__.py
afsk/afsk.py
afsk/ax25.py
afsk.egg-info/PKG-INFO
afsk.egg-info/SOURCES.txt
afsk.egg-info/dependency_links.txt
afsk.egg-info/entry_points.txt
afsk.egg-info/requires.txt
afsk.egg-info/top_level.txt