Metadata-Version: 1.0
Name: afsk
Version: 0.0.2
Summary: AFSK – Bell 202 Audio Frequency Shift Keying encoder
Home-page: https://github.com/casebeer/afsk
Author: Christopher H. Casebeer
Author-email: UNKNOWN
License: UNKNOWN
Platform: UNKNOWN
Classifier: Environment :: Console
Classifier: License :: OSI Approved :: BSD License
Classifier: Intended Audience :: Developers
Classifier: Topic :: Multimedia :: Sound/Audio
Classifier: Topic :: Communications :: Ham Radio
